{
  "language": "en",
  "words": [
    "androidx",
    "animable",
    "animatable",
    "appcompat",
    "automagically",
    "barfoo",
    "bfrg",
    "bridgeless",
    "chlgm",
    "coef",
    "collapsable",
    "devs",
    "easings",
    "inout",
    "ispreview",
    "layoutable",
    "lightspeed",
    "nomalized",
    "overdamped",
    "pressable",
    "RCTUI",
    "REAUI",
    "relayout",
    "runtimes",
    "snapshotting",
    "springify",
    "superview",
    "swmansion",
    "systrace",
    "threejs",
    "typecheck",
    "uimanager",
    "uimodule",
    "unmock",
    "usehooks",
    "worklet",
    "workletization",
    "workletize",
    "workletized",
    "workletizes",
    "worklets",
    "xcworkspace"
  ],
  "flagWords": ["ere", "hte", "truck", "trucker"],
  "ignorePaths": [
    "node_modules",
    "docs/src/components/Testimonials",
    "MacOSExample/macos/MacOSExample.xcodeproj",
    "app/src/examples/RuntimeTests/ReanimatedRuntimeTestsRunner/Presets.ts",
    "cspell.json",
    "package.json"
  ],
  "useGitignore": true
}
